arifETS/__init__.py
arifETS/expense_management.py
arifexpenseTS/__init__.py
arifexpenseTS/expense_management.py
arifETS-0.1.1.dist-info/LICENSE
arifETS-0.1.1.dist-info/METADATA
arifETS-0.1.1.dist-info/WHEEL
arifETS-0.1.1.dist-info/entry_points.txt
arifETS-0.1.1.dist-info/top_level.txt
arifETS-0.1.1.dist-info/RECORD
