Metadata-Version: 2.1
Name: arifETS
Version: 0.1.1
Summary: A simple expense tracking package
Home-page: https://github.com/yourusername/arifETS
Author: Arif Mustafa
Author-email: arifmustafa75@gmail.com
Classifier: Programming Language :: Python :: 3
Classifier: License :: OSI Approved :: MIT License
Classifier: Operating System :: OS Independent
Requires-Python: >=3.6
License-File: LICENSE
Requires-Dist: matplotlib
